LICENCE
MANIFEST.in
README.md
requirements.txt
setup.py
version
docs/Makefile
docs/conf.py
docs/index.rst
docs/install.rst
docs/isc.rst
docs/_static/ccfh.png
docs/_themes/.gitignore
docs/_themes/LICENSE
docs/_themes/README
docs/_themes/flask_theme_support.py
docs/_themes/flask/layout.html
docs/_themes/flask/relations.html
docs/_themes/flask/theme.conf
docs/_themes/flask/static/flasky.css_t
docs/_themes/flask/static/small_flask.css
docs/_themes/flask_small/layout.html
docs/_themes/flask_small/theme.conf
docs/_themes/flask_small/static/flasky.css_t
spcchart/__init__.py
spcchart/spc.py
spcchart/spcchart.py
spcchart/web.py
spcchart.egg-info/PKG-INFO
spcchart.egg-info/SOURCES.txt
spcchart.egg-info/dependency_links.txt
spcchart.egg-info/entry_points.txt
spcchart.egg-info/not-zip-safe
spcchart.egg-info/requires.txt
spcchart.egg-info/top_level.txt