Metadata-Version: 1.0
Name: spcchart
Version: 0.23
Summary: SPC Charts For Humans
Home-page: spc.io
Author: Ben Hughes
Author-email: bwghughes@gmail.com
License: BSD
Keywords: statistics,spc,chart,tool,process control
Platform: UNKNOWN
